{
  "configVersion": 1,
  "index": "/index.html",
  "assetGroups": [
    {
      "name": "app",
      "installMode": "prefetch",
      "updateMode": "prefetch",
      "urls": [
        "/assets/images/calendar_clock_icon.svg",
        "/assets/images/loader.svg",
        "/assets/images/pencil_icon.svg",
        "/assets/images/todo_list_icon.svg",
        "/cloud-messaging-sw.js",
        "/favicon.ico",
        "/index.html",
        "/main.d7746ce7af80bb524df2.js",
        "/polyfills.4c686a24ea7995742446.js",
        "/runtime.ec2944dd8b20ec099bf3.js",
        "/styles.ced7e44d10ae11f25eb2.css"
      ],
      "patterns": []
    },
    {
      "name": "assets/icons",
      "installMode": "lazy",
      "updateMode": "prefetch",
      "urls": [
        "/assets/icons/icon-128x128.png",
        "/assets/icons/icon-144x144.png",
        "/assets/icons/icon-152x152.png",
        "/assets/icons/icon-192x192.png",
        "/assets/icons/icon-384x384.png",
        "/assets/icons/icon-512x512.png",
        "/assets/icons/icon-72x72.png",
        "/assets/icons/icon-96x96.png"
      ],
      "patterns": []
    }
  ],
  "dataGroups": [],
  "hashTable": {
    "/assets/icons/icon-128x128.png": "b4d19cea4ac5ee406c94d114a6c292e5c23123e6",
    "/assets/icons/icon-144x144.png": "f14f267bba15fee52931c4a691ca0780e9b38805",
    "/assets/icons/icon-152x152.png": "de64689d7b8a36f7243802fe64463b0eed81b423",
    "/assets/icons/icon-192x192.png": "3bef27a885265c58c8b0ffae05f54c34c3b062d4",
    "/assets/icons/icon-384x384.png": "fa8cdd026f56fcb1156f58d8721f8ac87c19cdde",
    "/assets/icons/icon-512x512.png": "96da578c694a1a47cb8493ffc6b8abe65f335cf5",
    "/assets/icons/icon-72x72.png": "3f5e8f2e4a4db4e94e83f3c6f5e21decd9bdc1b1",
    "/assets/icons/icon-96x96.png": "d9c934ea4ed023bc86c08f474ee0b75140249699",
    "/assets/images/calendar_clock_icon.svg": "48c4ce01cd7ed7f16145623d4b05632d176cd392",
    "/assets/images/loader.svg": "0871743a430d8e961266c35f50656c938341a76f",
    "/assets/images/pencil_icon.svg": "ad4dca69d42313239d41184c9ffe40506ee46b67",
    "/assets/images/todo_list_icon.svg": "43d9577d79e76c329e14a4c732a81ed0153ce3dd",
    "/cloud-messaging-sw.js": "672285803e04254f2435ecc170b5338a6dce4498",
    "/favicon.ico": "2519202ab11d2d9542e3200665552c4d4bd874f0",
    "/index.html": "d578f649df0618c3315225eae42a79bc70f69eb9",
    "/main.d7746ce7af80bb524df2.js": "71b2b4b18d1e80f30a0534f421d8067bb572cb9f",
    "/polyfills.4c686a24ea7995742446.js": "4ab98e11e44c4bc97507dfc711f8420a47d6f18e",
    "/runtime.ec2944dd8b20ec099bf3.js": "b62956c2192bfe5516d6374e753773901ed50ec5",
    "/styles.ced7e44d10ae11f25eb2.css": "6c51f96fc173d9a252170772059046e9abc2268b"
  },
  "navigationUrls": [
    {
      "positive": true,
      "regex": "^\\/.*$"
    },
    {
      "positive": false,
      "regex": "^\\/(?:.+\\/)?[^/]*\\.[^/]*$"
    },
    {
      "positive": false,
      "regex": "^\\/(?:.+\\/)?[^/]*__[^/]*$"
    },
    {
      "positive": false,
      "regex": "^\\/(?:.+\\/)?[^/]*__[^/]*\\/.*$"
    }
  ]
}